poseigen_compass.py
poseigen_compass-0.0.2.dist-info/LICENSE.txt
poseigen_compass-0.0.2.dist-info/METADATA
poseigen_compass-0.0.2.dist-info/WHEEL
poseigen_compass-0.0.2.dist-info/RECORD
