Metadata-Version: 2.3
Name: poseigen_compass
Version: 0.0.2
Summary: The basics for Poseigen software
License: MIT
Author: Husam Abdulnabi
Author-email: husam.abdulnabi@gmail.com
Maintainer: Husam Abdulnabi
Maintainer-email: husam.abdulnabi@gmail.com
Requires-Python: >=3.12
Classifier: Development Status :: 3 - Alpha
Classifier: Intended Audience :: Developers
Classifier: Topic :: Software Development
Classifier: Programming Language :: Python :: 3
Requires-Dist: numpy
Requires-Dist: pandas
Requires-Dist: poseigen_seaside
Project-URL: Homepage, https://github.com/husam94/poseigen_compass
